orientseq/__init__.py
orientseq/__main__.py
orientseq-0.2.3.dist-info/METADATA
orientseq-0.2.3.dist-info/WHEEL
orientseq-0.2.3.dist-info/entry_points.txt
orientseq-0.2.3.dist-info/RECORD
